py_id/__init__.py
py_id/__version__.py
py_id/cli.py
py_id/include.py
py_id/main.py
py_id/process.py
py_id/util.py
py_id/enum/__init__.py
py_id/enum/effected.py
py_id/enum/file_error.py
py_id/enum/token_error.py
python_indo-0.0.11.dist-info/LICENSE.md
python_indo-0.0.11.dist-info/METADATA
python_indo-0.0.11.dist-info/WHEEL
python_indo-0.0.11.dist-info/entry_points.txt
python_indo-0.0.11.dist-info/top_level.txt
python_indo-0.0.11.dist-info/RECORD
