Metadata-Version: 2.1
Name: python-indo
Version: 0.0.11
Summary: an open source programming language, an interpreter to be precise, where you can write Python code using Bahasa Indonesia.
Home-page: https://github.com/madewgn
Author: Lantip
Author-email: lantip@underpaidworkers.org
License: MIT
Classifier: License :: OSI Approved :: MIT License
Classifier: Programming Language :: Python
Classifier: Programming Language :: Python :: 3
Classifier: Programming Language :: Python :: 3.6
Classifier: Programming Language :: Python :: 3.7
Classifier: Programming Language :: Python :: 3.8
Classifier: Programming Language :: Python :: Implementation :: CPython
Requires-Python: >=3.6.0
License-File: LICENSE.md
